{
  "home_dir": "/work/your/path/to/data-repo",
  "singularity_image": "/work/your/path/to/container.sif",
  "results_dir": ".",
  "branches": [
    "master",
    "EPTA+InPTA"
  ],
  "reference_branch": "master",
  "pulsars": "ALL",
  "outdir_name": null,
  "epoch": "55000",
  "force_rerun": false,
  "run_tempo2": true,
  "make_toa_coverage_plots": true,
  "make_change_reports": true,
  "make_covariance_heatmaps": true,
  "make_residual_plots": true,
  "make_outlier_reports": true,

  "run_fix_dataset": false,
  "make_binary_analysis": false,

  "pqc_gaussian_bump_enabled": false,
  "pqc_gaussian_bump_min_duration_days": 60.0,
  "pqc_gaussian_bump_max_duration_days": 1500.0,
  "pqc_gaussian_bump_n_durations": 6,
  "pqc_gaussian_bump_min_points": 20,
  "pqc_gaussian_bump_delta_chi2_thresh": 25.0,
  "pqc_gaussian_bump_suppress_overlap": true,
  "pqc_gaussian_bump_member_eta": 1.0,
  "pqc_gaussian_bump_freq_dependence": true,
  "pqc_gaussian_bump_freq_alpha_min": 0.0,
  "pqc_gaussian_bump_freq_alpha_max": 4.0,
  "pqc_gaussian_bump_freq_alpha_tol": 1e-3,
  "pqc_gaussian_bump_freq_alpha_max_iter": 64,

  "pqc_glitch_enabled": false,
  "pqc_glitch_min_points": 30,
  "pqc_glitch_delta_chi2_thresh": 25.0,
  "pqc_glitch_suppress_overlap": true,
  "pqc_glitch_member_eta": 1.0,
  "pqc_glitch_peak_tau_days": 30.0,
  "pqc_glitch_noise_k": 1.0,
  "pqc_glitch_mean_window_days": 180.0,
  "pqc_glitch_min_duration_days": 1000.0,

  "fix_update_alltim_includes": true,
  "fix_min_toas_per_backend_tim": 10,
  "fix_required_tim_flags": {},
  "fix_insert_missing_jumps": true,
  "fix_jump_flag": "-sys",
  "fix_ensure_ephem": null,
  "fix_ensure_clk": null,
  "fix_ensure_ne_sw": null,
  "fix_remove_patterns": ["NRT.NUPPI.", "NRT.NUXPI."],
  "fix_coord_convert": null,

  "binary_only_models": null,

  "dpi": 120,
  "max_covmat_params": null
}
